electrovoyage_asset_unpacker/__init__.py
electrovoyage_asset_unpacker/__init_legacy__.py
electrovoyage_asset_unpacker/exceptions.py
electrovoyage_asset_unpacker-2.0.1.dist-info/LICENSE
electrovoyage_asset_unpacker-2.0.1.dist-info/METADATA
electrovoyage_asset_unpacker-2.0.1.dist-info/WHEEL
electrovoyage_asset_unpacker-2.0.1.dist-info/top_level.txt
electrovoyage_asset_unpacker-2.0.1.dist-info/RECORD
